armpicom/__init__.py
armpicom/py.typed
armpicom/conf/armpicom.cfg
armpicom/conf/armpicom.logo
armpicom/conf/armpicom_util.cfg
armpicom/conf/project.yaml
armpicom/conf/template/CMakeLists.template
armpicom/conf/template/pico_sdk_import.template
armpicom/conf/template/pro_auto_set_url.template
armpicom/conf/template/build/armpicom.md
armpicom/conf/template/src/CMakeLists.template
armpicom/conf/template/src/main.template
armpicom/log/armpicom.log
armpicom/pro/__init__.py
armpicom/pro/read_template.py
armpicom/pro/write_template.py
armpicom-1.9.3.dist-info/licenses/LICENSE
usr/local/bin/armpicom_run.py
armpicom-1.9.3.dist-info/METADATA
armpicom-1.9.3.dist-info/WHEEL
armpicom-1.9.3.dist-info/top_level.txt
armpicom-1.9.3.dist-info/RECORD
