Metadata-Version: 2.4
Name: armpicom
Version: 1.9.3
Summary: Python package for generation of RPI configuration/build
Home-page: https://vroncevic.github.io/armpicom
Author: Vladimir Roncevic
Author-email: elektron.ronca@gmail.com
License: GPL-3.0-or-later
Keywords: setup,python,install,RPI Pico,CMake,generator
Platform: any
Classifier: Programming Language :: Python :: 3.10
Classifier: Programming Language :: Python :: 3.11
Classifier: Programming Language :: Python :: 3.12
License-File: LICENSE
Requires-Dist: ats-utilities
Dynamic: author
Dynamic: author-email
Dynamic: classifier
Dynamic: description
Dynamic: description-content-type
Dynamic: home-page
Dynamic: keywords
Dynamic: license
Dynamic: license-file
Dynamic: platform
Dynamic: requires-dist
Dynamic: summary
